cloudkitty_tempest_plugin/README.rst
cloudkitty_tempest_plugin/__init__.py
cloudkitty_tempest_plugin/config.py
cloudkitty_tempest_plugin/plugin.py
cloudkitty_tempest_plugin/services/__init__.py
cloudkitty_tempest_plugin/services/client.py
cloudkitty_tempest_plugin/tests/__init__.py
cloudkitty_tempest_plugin/tests/api/__init__.py
cloudkitty_tempest_plugin/tests/api/base.py
cloudkitty_tempest_plugin/tests/api/v1/__init__.py
cloudkitty_tempest_plugin/tests/api/v1/test_cloudkitty_api.py
cloudkitty_tempest_plugin/tests/api/v1/test_hashmap_api.py
cloudkitty_tempest_plugin/tests/api/v1/test_pyscript_api.py
cloudkitty_tempest_plugin/tests/api/v2/__init__.py
cloudkitty_tempest_plugin/tests/scenario/__init__.py
cloudkitty_tempest_plugin-3.3.0.dist-info/AUTHORS
cloudkitty_tempest_plugin-3.3.0.dist-info/LICENSE
cloudkitty_tempest_plugin-3.3.0.dist-info/METADATA
cloudkitty_tempest_plugin-3.3.0.dist-info/WHEEL
cloudkitty_tempest_plugin-3.3.0.dist-info/entry_points.txt
cloudkitty_tempest_plugin-3.3.0.dist-info/pbr.json
cloudkitty_tempest_plugin-3.3.0.dist-info/top_level.txt
cloudkitty_tempest_plugin-3.3.0.dist-info/RECORD
