Metadata-Version: 2.1
Name: cloudkitty_tempest_plugin
Version: 3.3.0
Summary: Tempest plugin for CloudKitty
Home-page: https://opendev.org/openstack/cloudkitty-tempest-plugin
Author: OpenStack
Author-email: openstack-discuss@lists.openstack.org
Classifier: Environment :: OpenStack
Classifier: Intended Audience :: Information Technology
Classifier: Intended Audience :: System Administrators
Classifier: License :: OSI Approved :: Apache Software License
Classifier: Operating System :: POSIX :: Linux
Classifier: Programming Language :: Python
Classifier: Programming Language :: Python :: 3
Classifier: Programming Language :: Python :: 3.9
Classifier: Programming Language :: Python :: 3.10
Classifier: Programming Language :: Python :: 3.11
Classifier: Programming Language :: Python :: 3.12
License-File: LICENSE
License-File: AUTHORS
Requires-Dist: keystoneauth1 >=2.18.0
Requires-Dist: oslo.config >=3.18.0
Requires-Dist: oslo.serialization >=2.14.0
Requires-Dist: pbr >=2.0
Requires-Dist: python-keystoneclient >=3.6.0
Requires-Dist: tempest >=15.0.0
